lib_V1-0.0.7.dist-info/WHEEL
lib_V1-0.0.7.dist-info/top_level.txt
lib_V1-0.0.7.dist-info/METADATA
lib_V1-0.0.7.dist-info/RECORD
lib_dsa/byte_array_st.cpython-38-x86_64-linux-gnu.so
lib_dsa/segmented_reader.cpython-38-x86_64-linux-gnu.so
lib_dsa/graph_db.cpython-38-x86_64-linux-gnu.so
lib_dsa/kv_db.cpython-38-x86_64-linux-gnu.so
lib_dsa/byte_array.cpython-38-x86_64-linux-gnu.so
lib_dsa/__init__.cpython-38-x86_64-linux-gnu.so
lib_dsa/mem_structs.cpython-38-x86_64-linux-gnu.so
lib_py_parse/parse_skeleton.cpython-38-x86_64-linux-gnu.so
lib_py_parse/parse_L0_skeleton.cpython-38-x86_64-linux-gnu.so
lib_py_parse/__api__.cpython-38-x86_64-linux-gnu.so
lib_py_parse/__init__.cpython-38-x86_64-linux-gnu.so
lib_py_parse/parser.cpython-38-x86_64-linux-gnu.so
lib_py_parse/utils/constants.cpython-38-x86_64-linux-gnu.so
lib_py_parse/utils/parsing_utils.cpython-38-x86_64-linux-gnu.so
lib_py_parse/utils/fmt_utils.cpython-38-x86_64-linux-gnu.so
lib_py_parse/utils/exceptions.cpython-38-x86_64-linux-gnu.so
lib_py_parse/utils/__init__.cpython-38-x86_64-linux-gnu.so
lib_py_parse/helper/type_resolver.cpython-38-x86_64-linux-gnu.so
lib_py_parse/helper/__init__.cpython-38-x86_64-linux-gnu.so
lib_py_parse/helper/eval_service.cpython-38-x86_64-linux-gnu.so
lib_py_parse/helper/eval_helper.cpython-38-x86_64-linux-gnu.so
lib_compute/scrape_utils.cpython-38-x86_64-linux-gnu.so
lib_compute/serialization.cpython-38-x86_64-linux-gnu.so
lib_compute/partitioning.cpython-38-x86_64-linux-gnu.so
lib_compute/deserialization.cpython-38-x86_64-linux-gnu.so
lib_compute/typon_math.cpython-38-x86_64-linux-gnu.so
lib_compute/map_rdx.cpython-38-x86_64-linux-gnu.so
lib_compute/__init__.cpython-38-x86_64-linux-gnu.so
lib_compute/M3/m3.cpython-38-x86_64-linux-gnu.so
lib_compute/M3/__init__.cpython-38-x86_64-linux-gnu.so
lib_typ_parse/parse_skeleton.cpython-38-x86_64-linux-gnu.so
lib_typ_parse/parse_L0_skeleton.cpython-38-x86_64-linux-gnu.so
lib_typ_parse/__api__.cpython-38-x86_64-linux-gnu.so
lib_typ_parse/__init__.cpython-38-x86_64-linux-gnu.so
lib_typ_parse/parser.cpython-38-x86_64-linux-gnu.so
