Metadata-Version: 2.1
Name: lib-V1
Version: 0.0.7
Summary: UNKNOWN
Home-page: http://pypi.python.org/pypi/lib_V1/0.0.7
Author: Algorithms Path
Author-email: support@algorithmspath.com
License: MIT
Platform: UNKNOWN
Requires-Dist: bs4
Requires-Dist: plyvel
Requires-Dist: selenium
